python_lauterbach/__init__.py
python_lauterbach/python_lauterbach.py
python_lauterbach-0.0.2.dist-info/LICENSE
python_lauterbach-0.0.2.dist-info/METADATA
python_lauterbach-0.0.2.dist-info/WHEEL
python_lauterbach-0.0.2.dist-info/top_level.txt
python_lauterbach-0.0.2.dist-info/RECORD
