Metadata-Version: 2.1
Name: python-lauterbach
Version: 0.0.2
Summary: Python Lauterbach Automation
Home-page: https://github.com/sgnes/python_lauterbach
Author: Guopeng Sun
Author-email: sgnes0514@gmai.com
Classifier: Programming Language :: Python :: 3
Classifier: License :: OSI Approved :: MIT License
Classifier: Operating System :: OS Independent
Requires-Python: >=3.6
License-File: LICENSE
Requires-Dist: lauterbach-trace32-rcl
Requires-Dist: loguru
